CL_Dynamic_Test_Case_Library/CL_Dynamic_Test_Case_Library.py
CL_Dynamic_Test_Case_Library/__init__.py
CL_Dynamic_Test_Case_Library-1.1.dist-info/LICENSE.txt
CL_Dynamic_Test_Case_Library-1.1.dist-info/METADATA
CL_Dynamic_Test_Case_Library-1.1.dist-info/WHEEL
CL_Dynamic_Test_Case_Library-1.1.dist-info/top_level.txt
CL_Dynamic_Test_Case_Library-1.1.dist-info/RECORD
